{"host":"222222222m323qr3.onion","path":"/","port":"","protocol":"http","uriPath":"/","url":"http://222222222m323qr3.onion/","depth":1,"fetched":true,"status":"downloaded","stateData":{"requestLatency":16248,"requestTime":16342,"contentLength":22425,"contentType":"text/html; charset=utf-8","code":200,"headers":{"x-powered-by":"Express","content-type":"text/html; charset=utf-8","content-length":"22425","etag":"W/\"5799-5cSEjgSkcdctXUjMpzpoN+U3Kbo\"","date":"Sat, 25 Jan 2020 14:46:10 GMT","connection":"close"},"downloadTime":94,"actualDataSize":22425,"sentIncorrectSize":false},"id":0}